ahorn_loader/__init__.py
ahorn_loader/api.py
ahorn_loader/cli.py
ahorn_loader/py.typed
ahorn_loader/utils/__init__.py
ahorn_loader/utils/cache.py
ahorn_loader/validator/__init__.py
ahorn_loader/validator/rules.py
ahorn_loader/validator/validator.py
ahorn_loader-0.3.0.dist-info/WHEEL
ahorn_loader-0.3.0.dist-info/entry_points.txt
ahorn_loader-0.3.0.dist-info/METADATA
ahorn_loader-0.3.0.dist-info/RECORD
