Metadata-Version: 2.4
Name: ahorn-loader
Version: 0.3.0
Summary: Library and command-line application to interact with datasets in the Aachen Higher-Order Repository of Networks.
Author: Florian Frantzen
Author-email: Florian Frantzen <frantzen@netsci.rwth-aachen.de>
License-Expression: MIT
Classifier: Development Status :: 4 - Beta
Classifier: Intended Audience :: Developers
Classifier: Intended Audience :: Science/Research
Classifier: Operating System :: OS Independent
Classifier: Programming Language :: Python :: 3
Classifier: Programming Language :: Python :: 3 :: Only
Classifier: Programming Language :: Python :: 3.12
Classifier: Programming Language :: Python :: 3.13
Classifier: Programming Language :: Python :: 3.14
Classifier: Topic :: Scientific/Engineering
Requires-Dist: requests>=2.32.4
Requires-Dist: typer>=0.16.0
Requires-Python: >=3.12
